yelp_logging/__init__.py
yelp_cong7gan-4.17.0.dist-info/METADATA
yelp_cong7gan-4.17.0.dist-info/WHEEL
yelp_cong7gan-4.17.0.dist-info/top_level.txt
yelp_cong7gan-4.17.0.dist-info/RECORD
