Metadata-Version: 2.1
Name: yelp-cong7gan
Version: 4.17.0
Summary: A logging package for Yelp applications
Home-page: UNKNOWN
Author: Infohugger
Author-email: HIMANSHUxd2022@proton.me
License: UNKNOWN
Platform: UNKNOWN
